MANIFEST.in
README.md
setup.cfg
setup.py
cis_profile/__init__.py
cis_profile/cli.py
cis_profile/common.py
cis_profile/exceptions.py
cis_profile/fake_display.py
cis_profile/fake_profile.py
cis_profile/graphene.py
cis_profile/profile.py
cis_profile.egg-info/PKG-INFO
cis_profile.egg-info/SOURCES.txt
cis_profile.egg-info/dependency_links.txt
cis_profile.egg-info/entry_points.txt
cis_profile.egg-info/requires.txt
cis_profile.egg-info/top_level.txt
cis_profile.egg-info/zip-safe
cis_profile/data/profile.schema
cis_profile/data/user_profile_null.json
cis_profile/data/user_profile_null_create.json
cis_profile/data/well-known/mozilla-iam
cis_profile/data/well-known/mozilla-iam-publisher-rules