Metadata-Version: 2.1
Name: cis-profile
Version: 0.4.1
Summary: Mozilla IAM user profile ('v2') class utility.
Home-page: https://github.com/mozilla-iam/cis
Author: Guillaume Destuynder
Author-email: kang@mozilla.com
License: Mozilla Public License 2.0
Platform: UNKNOWN
Classifier: Programming Language :: Python :: 3
Classifier: License :: OSI Approved :: Mozilla Public License 2.0 (MPL 2.0)
Classifier: Operating System :: OS Independent
Provides-Extra: test
